ddns/__builtins__.pyi
ddns/__init__.py
ddns/__main__.py
ddns/cache.py
ddns/ip.py
ddns/config/__init__.py
ddns/config/cli.py
ddns/config/config.py
ddns/config/env.py
ddns/config/file.py
ddns/provider/__init__.py
ddns/provider/_base.py
ddns/provider/_signature.py
ddns/provider/alidns.py
ddns/provider/aliesa.py
ddns/provider/callback.py
ddns/provider/cloudflare.py
ddns/provider/debug.py
ddns/provider/dnscom.py
ddns/provider/dnspod.py
ddns/provider/dnspod_com.py
ddns/provider/edgeone.py
ddns/provider/edgeone_dns.py
ddns/provider/he.py
ddns/provider/huaweidns.py
ddns/provider/namesilo.py
ddns/provider/noip.py
ddns/provider/tencentcloud.py
ddns/scheduler/__init__.py
ddns/scheduler/_base.py
ddns/scheduler/cron.py
ddns/scheduler/launchd.py
ddns/scheduler/schtasks.py
ddns/scheduler/systemd.py
ddns/util/__init__.py
ddns/util/comment.py
ddns/util/fileio.py
ddns/util/http.py
ddns/util/try_run.py
ddns-4.1.3.dist-info/licenses/LICENSE
ddns-4.1.3.dist-info/METADATA
ddns-4.1.3.dist-info/WHEEL
ddns-4.1.3.dist-info/entry_points.txt
ddns-4.1.3.dist-info/top_level.txt
ddns-4.1.3.dist-info/RECORD
