Metadata-Version: 2.4
Name: ddns
Version: 4.1.3
Summary: Dynamic DNS client for multiple providers, supporting IPv4 and IPv6.
Author-email: NewFuture <python@newfuture.cc>
License-Expression: MIT
Project-URL: Homepage, https://ddns.newfuture.cc
Project-URL: Documentation, https://ddns.newfuture.cc
Project-URL: Repository, https://github.com/NewFuture/DDNS
Project-URL: Bug Tracker, https://github.com/NewFuture/DDNS/issues
Project-URL: Source, https://github.com/NewFuture/DDNS
Keywords: ddns,ipv6,ipv4,dns,dnspod,alidns,cloudflare
Platform: any
Classifier: Development Status :: 5 - Production/Stable
Classifier: Intended Audience :: Developers
Classifier: Intended Audience :: End Users/Desktop
Classifier: Intended Audience :: Information Technology
Classifier: Intended Audience :: System Administrators
Classifier: Topic :: Internet
Classifier: Topic :: Internet :: Name Service (DNS)
Classifier: Topic :: System :: Networking
Classifier: Topic :: Software Development
Classifier: Programming Language :: Python :: 2.7
Classifier: Programming Language :: Python :: 3
Classifier: Programming Language :: Python :: 3.6
Classifier: Programming Language :: Python :: 3.7
Classifier: Programming Language :: Python :: 3.8
Classifier: Programming Language :: Python :: 3.9
Classifier: Programming Language :: Python :: 3.10
Classifier: Programming Language :: Python :: 3.11
Classifier: Programming Language :: Python :: 3.12
Classifier: Programming Language :: Python :: 3.13
Requires-Python: >=2.7
License-File: LICENSE
Provides-Extra: dev
Requires-Dist: ruff; extra == "dev"
Requires-Dist: mock; python_version < "3.3" and extra == "dev"
Provides-Extra: pytest
Requires-Dist: pytest>=6.0; extra == "pytest"
Requires-Dist: pytest-cov; extra == "pytest"
Requires-Dist: mock; python_version < "3.3" and extra == "pytest"
Dynamic: license-file
